{
    "epiENGAGE-baseline": {
        "target_end_date": [
            "2025-02-22",
            "2025-03-01",
            "2025-03-08",
            "2025-03-15",
            "2025-03-22"
        ],
        "q0.025": [
            1.65405855855856,
            0.909388138138139,
            0.569056306306305,
            0.397210210210208,
            0.0
        ],
        "q0.25": [
            3.9025,
            3.74,
            3.2466966966967,
            3.07376126126126,
            2.93368618618619
        ],
        "q0.5": [
            4.01,
            4.01,
            4.01,
            4.01,
            4.01
        ],
        "q0.75": [
            4.1175,
            4.30709459459459,
            4.73111111111111,
            5.00627627627627,
            5.17265015015015
        ],
        "q0.975": [
            6.36594144144144,
            6.91084234234234,
            7.3476951951952,
            7.45038888888889,
            8.01699699699699
        ]
    },
    "epiforecasts-dyngam": {
        "target_end_date": [
            "2025-02-22",
            "2025-03-01",
            "2025-03-08",
            "2025-03-15",
            "2025-03-22",
            "2025-03-29"
        ],
        "q0.025": [
            2.4406035,
            1.48222575,
            0.92401175,
            0.58699895,
            0.395586775,
            0.262989975
        ],
        "q0.25": [
            3.55039,
            2.5227525,
            1.8564925,
            1.30403,
            0.96634675,
            0.760017
        ],
        "q0.5": [
            4.359375,
            3.33296,
            2.59923,
            1.98566,
            1.54306,
            1.22805
        ],
        "q0.75": [
            5.26278,
            4.34325,
            3.5607875,
            2.9486475,
            2.4696725,
            1.9982125
        ],
        "q0.975": [
            7.49244125,
            7.10165025,
            6.64398599999999,
            5.57664375,
            5.00494424999999,
            4.58752649999999
        ]
    },
    "epiENGAGE-Copycat": {
        "target_end_date": [
            "2025-03-01",
            "2025-03-08",
            "2025-03-15",
            "2025-03-22",
            "2025-03-29"
        ],
        "q0.025": [
            1,
            0,
            0,
            0,
            0
        ],
        "q0.25": [
            3,
            2,
            1,
            1,
            1
        ],
        "q0.5": [
            4,
            4,
            3,
            2,
            2
        ],
        "q0.75": [
            6,
            5,
            4,
            4,
            3
        ],
        "q0.975": [
            10,
            9,
            8,
            7,
            7
        ]
    },
    "epiENGAGE-lop_norm": {
        "target_end_date": [
            "2025-02-22",
            "2025-03-01",
            "2025-03-08",
            "2025-03-15",
            "2025-03-22",
            "2025-03-29"
        ],
        "q0.025": [
            2.54973896330265,
            1.35405298044197,
            0.734244090890133,
            0.0,
            0.0,
            0.0
        ],
        "q0.25": [
            3.79782046393137,
            3.02703396302278,
            2.33804594969184,
            1.74752412477742,
            1.30131305195416,
            0.819359312784087
        ],
        "q0.5": [
            4.33879932618246,
            3.85331276043528,
            3.50646549913696,
            2.79147539049336,
            2.42713568453557,
            1.54233582856887
        ],
        "q0.75": [
            5.10653470769812,
            4.67105580654988,
            4.19765954516681,
            3.50431100754078,
            3.05649994740105,
            2.55273619316056
        ],
        "q0.975": [
            7.6791798949431,
            8.45767062041983,
            7.73138747901272,
            6.8387162827332,
            6.20134555660861,
            6.17155765163347
        ]
    },
    "epiENGAGE-GBQR": {
        "target_end_date": [
            "2025-02-22",
            "2025-03-01",
            "2025-03-08",
            "2025-03-15",
            "2025-03-22"
        ],
        "q0.025": [
            2.50378288590467,
            2.48165678338376,
            1.98100573623319,
            1.48266139527705,
            1.27392899689935
        ],
        "q0.25": [
            3.97604448622451,
            3.83799212753784,
            3.48171211951569,
            2.75550751314168,
            2.51745906928338
        ],
        "q0.5": [
            4.26222411671197,
            3.85865373920502,
            3.55100675461862,
            2.91809273104277,
            2.70754645877846
        ],
        "q0.75": [
            4.39754093462614,
            4.07562688070245,
            3.56649522943606,
            3.26547830960986,
            3.04135867911752
        ],
        "q0.975": [
            5.74234550127682,
            5.71773464924349,
            5.50423754011124,
            5.63845851098921,
            6.302450834851
        ]
    },
    "epiENGAGE-ensemble_mean": {
        "target_end_date": [
            "2025-02-22",
            "2025-03-01",
            "2025-03-08",
            "2025-03-15",
            "2025-03-22",
            "2025-03-29"
        ],
        "q0.025": [
            2.55263306832102,
            1.66568732950769,
            1.02386200963967,
            0.73564883782737,
            0.556505257299783,
            0.1314949875
        ],
        "q0.25": [
            3.81923788864734,
            3.11118713690261,
            2.41613503828529,
            1.73047450097846,
            1.49460193976113,
            0.8800085
        ],
        "q0.5": [
            4.48912574034514,
            3.82128850165813,
            3.3430246488477,
            2.65288811583362,
            2.08353548625949,
            1.614025
        ],
        "q0.75": [
            5.19155545460383,
            4.91105405347264,
            4.14371087414403,
            3.49970177452748,
            3.17034372637251,
            2.49910625
        ],
        "q0.975": [
            7.16630971466662,
            7.73330740052285,
            7.26613594258585,
            6.56077166257067,
            6.10246502828366,
            5.79376325
        ]
    },
    "epiENGAGE-INFLAenza": {
        "target_end_date": [
            "2025-02-22",
            "2025-03-01",
            "2025-03-08",
            "2025-03-15"
        ],
        "q0.025": [
            2.7135128190584,
            1.698866784647,
            1.1904305523255,
            0.87293500603243
        ],
        "q0.25": [
            3.9312791797175,
            3.0840039200726,
            2.32633553362548,
            1.86236049077215
        ],
        "q0.5": [
            4.84577810432345,
            4.09354026742751,
            3.22186184077216,
            2.7077997322917
        ],
        "q0.75": [
            5.91434542918536,
            5.22533933318809,
            4.44756076714006,
            3.78468128850005
        ],
        "q0.975": [
            8.26414239272305,
            8.11384470284792,
            7.91632023023216,
            7.02798438929348
        ]
    }
}