{
    "epiENGAGE-baseline": {
        "target_end_date": [
            "2025-05-10",
            "2025-05-17",
            "2025-05-24",
            "2025-05-31",
            "2025-06-07"
        ],
        "q0.025": [
            121.215690690691,
            10.187937937938,
            0.0,
            0.0,
            0.0
        ],
        "q0.25": [
            372.0,
            343.492742742743,
            320.071071071071,
            291.388138138138,
            269.409159159159
        ],
        "q0.5": [
            406.0,
            406.0,
            406.0,
            406.0,
            406.0
        ],
        "q0.75": [
            440.0,
            473.808058058058,
            501.301051051051,
            521.587837837838,
            541.327327327327
        ],
        "q0.975": [
            690.784309309309,
            801.388013013012,
            874.126901901902,
            943.513963963963,
            1015.09094094094
        ]
    },
    "epiforecasts-dyngam": {
        "target_end_date": [
            "2025-05-10",
            "2025-05-17",
            "2025-05-24",
            "2025-05-31",
            "2025-06-07"
        ],
        "q0.025": [
            289.975,
            249.975,
            217.975,
            191.0,
            171.975
        ],
        "q0.25": [
            346.0,
            320.0,
            298.0,
            279.0,
            256.75
        ],
        "q0.5": [
            384.0,
            368.0,
            352.0,
            334.5,
            324.0
        ],
        "q0.75": [
            428.0,
            427.0,
            417.0,
            410.0,
            405.0
        ],
        "q0.975": [
            514.0,
            560.025,
            579.05,
            599.025,
            605.0
        ]
    },
    "epiENGAGE-Copycat": {
        "target_end_date": [
            "2025-05-10",
            "2025-05-17",
            "2025-05-24",
            "2025-05-31",
            "2025-06-07"
        ],
        "q0.025": [
            323.0,
            300.0,
            274.0,
            254.0,
            243.0
        ],
        "q0.25": [
            367.0,
            348.0,
            337.0,
            325.0,
            312.0
        ],
        "q0.5": [
            390.0,
            374.0,
            368.0,
            360.0,
            352.0
        ],
        "q0.75": [
            411.0,
            406.0,
            399.0,
            397.0,
            388.0
        ],
        "q0.975": [
            458.0,
            469.0,
            467.0,
            476.0,
            471.0
        ]
    },
    "epiENGAGE-lop_norm": {
        "target_end_date": [
            "2025-05-10",
            "2025-05-17",
            "2025-05-24",
            "2025-05-31"
        ],
        "q0.025": [
            270.155096526775,
            230.365018441977,
            184.80870193534,
            152.429269388618
        ],
        "q0.25": [
            357.077282308366,
            339.694791887764,
            324.612144040178,
            310.693905484517
        ],
        "q0.5": [
            390.696366539967,
            380.090227244982,
            368.525994220754,
            355.424632515839
        ],
        "q0.75": [
            427.930707367028,
            430.216899888704,
            423.346880571067,
            415.658639156119
        ],
        "q0.975": [
            531.823402405391,
            592.070111170019,
            652.673347435787,
            672.439596043705
        ]
    },
    "epiENGAGE-GBQR": {
        "target_end_date": [
            "2025-05-10",
            "2025-05-17",
            "2025-05-24",
            "2025-05-31",
            "2025-06-07"
        ],
        "q0.025": [
            303.134619996772,
            296.400310415326,
            290.232463161952,
            282.369376746654,
            280.709767363087
        ],
        "q0.25": [
            366.662221183598,
            356.270608248237,
            348.39080814556,
            338.381533989208,
            327.949092933815
        ],
        "q0.5": [
            391.14269464083,
            383.528844003083,
            366.740397383538,
            350.169351481417,
            343.152752569726
        ],
        "q0.75": [
            434.716474136025,
            426.977567184815,
            406.658585096176,
            389.213313633795,
            377.766522302348
        ],
        "q0.975": [
            475.781426828864,
            476.993283542271,
            476.263427238864,
            476.826709768888,
            475.744818456944
        ]
    },
    "epiENGAGE-ensemble_mean": {
        "target_end_date": [
            "2025-05-10",
            "2025-05-17",
            "2025-05-24",
            "2025-05-31"
        ],
        "q0.025": [
            257.665062137493,
            218.112649670653,
            199.24149263239,
            186.273875349331
        ],
        "q0.25": [
            355.73244423672,
            336.952670198196,
            321.492375843326,
            305.753934425469
        ],
        "q0.5": [
            389.228538928166,
            380.905768800617,
            370.948079476708,
            360.733870296283
        ],
        "q0.75": [
            428.943294827205,
            434.357125048575,
            431.791927229445,
            429.160230294327
        ],
        "q0.975": [
            540.918147227635,
            578.081259311057,
            605.688065828153,
            621.27313474657
        ]
    },
    "epiENGAGE-INFLAenza": {
        "target_end_date": [
            "2025-05-10",
            "2025-05-17",
            "2025-05-24",
            "2025-05-31"
        ],
        "q0.025": [
            251.0,
            234.0,
            214.0,
            204.0
        ],
        "q0.25": [
            327.0,
            317.0,
            304.0,
            295.0
        ],
        "q0.5": [
            375.0,
            373.0,
            362.0,
            353.0
        ],
        "q0.75": [
            431.0,
            438.0,
            435.0,
            428.0
        ],
        "q0.975": [
            566.025,
            583.0,
            632.0,
            611.0
        ]
    }
}